README.txt
setup.cfg
setup.py
scripts/jabbercrackyd.py
src/jabbercracky/__init__.py
src/jabbercracky/jabbercracky.py
src/jabbercracky.egg-info/PKG-INFO
src/jabbercracky.egg-info/SOURCES.txt
src/jabbercracky.egg-info/dependency_links.txt
src/jabbercracky.egg-info/top_level.txt