Metadata-Version: 1.0
Name: jabbercracky
Version: 0.1.0
Summary: A Hash-Cracking Web Service
Home-page: http://awgh.org
Author: awgh
Author-email: awgh@awgh.org
License: GPL
Keywords: hash crack md5 lm ntlm jabbercracky
Platform: UNKNOWN
Classifier: Programming Language :: Python
Classifier: Programming Language :: PHP
Classifier: Operating System :: POSIX
Classifier: Development Status :: 2 - Pre-Alpha
Classifier: Topic :: Security :: Cryptography
Classifier: Topic :: Internet :: WWW/HTTP
